{
  "s220515001": {
    "groups": [
      {
        "id": "45a34d0f-0846-4501-bee6-f28d26090474",
        "name": "暑假作业",
        "order": 0,
        "createdAt": 1782885580563,
        "tasks": [
          {
            "id": "93f1cc77-13ba-401e-aef4-0758eb90a082",
            "content": "语文%P1-2%%U1-3%",
            "completed": false,
            "order": 0,
            "createdAt": 1782893176889,
            "completedAt": null,
            "subtasks": [
              {
                "id": "ad712928-374b-4889-b22d-b2223b4f0259",
                "content": "第1页",
                "completed": false,
                "order": 0
              },
              {
                "id": "291c787d-3f91-4682-9a0c-a1b52b3c5602",
                "content": "第2页",
                "completed": false,
                "order": 1
              },
              {
                "id": "e62624e3-4980-463d-be98-d8e7a582ae10",
                "content": "第1单元",
                "completed": false,
                "order": 2
              },
              {
                "id": "7eaba189-d0b6-4a78-8cc7-c9d1d12cad9e",
                "content": "第2单元",
                "completed": false,
                "order": 3
              },
              {
                "id": "a0f1d3a7-4954-43c7-a454-e3a7c8518cdb",
                "content": "第3单元",
                "completed": false,
                "order": 4
              }
            ]
          },
          {
            "id": "a14bca0e-b8da-4646-a8c2-f36e0ce0d56d",
            "content": "语文%P1-2%",
            "completed": false,
            "order": 1,
            "createdAt": 1782893450239,
            "completedAt": null,
            "subtasks": [
              {
                "id": "b3a60022-5aa4-47d1-b036-be5d139d2477",
                "content": "第1页",
                "completed": false,
                "order": 0
              },
              {
                "id": "9eb761df-7a85-4eb8-a177-9f47e560c720",
                "content": "第2页",
                "completed": false,
                "order": 1
              }
            ]
          },
          {
            "id": "e783ebd6-3827-4c07-b7ec-27ce9f626541",
            "content": "数学",
            "completed": false,
            "order": 2,
            "createdAt": 1782893997050,
            "completedAt": null,
            "subtasks": [
              {
                "id": "7ab55bc2-b5bc-4f5f-8980-1cf953caeaa0",
                "content": "第2页",
                "completed": false,
                "order": 0
              },
              {
                "id": "1e43054b-5167-41ed-9a70-541f05ffb833",
                "content": "第1页",
                "completed": false,
                "order": 1
              }
            ]
          }
        ]
      }
    ]
  }
}